wiutils/__init__.py
wiutils/_domestic.py
wiutils/darwincore.py
wiutils/extraction.py
wiutils/filtering.py
wiutils/plotting.py
wiutils/preprocessing.py
wiutils/reading.py
wiutils/summarizing.py
wiutils/_dwc/__init__.py
wiutils/_dwc/countries.json
wiutils/_dwc/event.py
wiutils/_dwc/measurement.py
wiutils/_dwc/multimedia.py
wiutils/_dwc/occurrence.py
wiutils/_labels/__init__.py
wiutils/_labels/deployments.py
wiutils/_labels/images.py
wiutils/_utils/__init__.py
wiutils/_utils/taxonomy.py
wiutils/config/mplstyle
wiutils/data/cajambre.zip
wiutils/data/cristales.zip
wiutils-1.1.0.dist-info/LICENSE.txt
wiutils-1.1.0.dist-info/METADATA
wiutils-1.1.0.dist-info/WHEEL
wiutils-1.1.0.dist-info/top_level.txt
wiutils-1.1.0.dist-info/RECORD
